{"label":"Quarry - Quarry Mint Wrapper","latest":{"slug":"QuarryProtocol__quarry-v1.11.11","org":"QuarryProtocol","repoName":"quarry","source":"https://github.com/QuarryProtocol/quarry/tree/v1.11.11","tag":"v1.11.11","shasum":"b42dacbbe219deeb8f8f32638f6e7f1fe9a552c65543225da9f839efcff13275"},"releases":[{"slug":"QuarryProtocol__quarry-v1.10.2","org":"QuarryProtocol","repoName":"quarry","source":"https://github.com/QuarryProtocol/quarry/tree/v1.10.2","tag":"v1.10.2"},{"slug":"QuarryProtocol__quarry-v1.10.5","org":"QuarryProtocol","repoName":"quarry","source":"https://github.com/QuarryProtocol/quarry/tree/v1.10.5","tag":"v1.10.5"},{"slug":"QuarryProtocol__quarry-v1.11.3","org":"QuarryProtocol","repoName":"quarry","source":"https://github.com/QuarryProtocol/quarry/tree/v1.11.3","tag":"v1.11.3"},{"slug":"QuarryProtocol__quarry-v1.11.8","org":"QuarryProtocol","repoName":"quarry","source":"https://github.com/QuarryProtocol/quarry/tree/v1.11.8","tag":"v1.11.8"},{"slug":"QuarryProtocol__quarry-v1.11.11","org":"QuarryProtocol","repoName":"quarry","source":"https://github.com/QuarryProtocol/quarry/tree/v1.11.11","tag":"v1.11.11"}],"hasIDL":true}